Metadata-Version: 2.1
Name: Python.js
Version: 1.1.0
Summary: A python library for people who prefer JavaScript's way of handling things.
Home-page: https://github.com/Nemika-Haj/PyJS
Author: Nemika
Author-email: nemika@bytestobits.dev
License: MIT
Download-URL: https://github.com/Nemika-Haj/PyJS/archive/1.1.0.tar.gz
Keywords: pyjs,javascript,python,js,py.js,python.js,python js
Platform: UNKNOWN
Classifier: Intended Audience :: Developers
Classifier: Topic :: Software Development :: Build Tools
Classifier: License :: OSI Approved :: MIT License
Classifier: Programming Language :: Python :: 3
Classifier: Programming Language :: Python :: 3.4
Classifier: Programming Language :: Python :: 3.5
Classifier: Programming Language :: Python :: 3.6
Classifier: Programming Language :: Python :: 3.7
Classifier: Programming Language :: Python :: 3.8
Classifier: Programming Language :: Python :: 3.9
